bigfoot_video_generator/__init__.py
bigfoot_video_generator-1767666.962.997.dist-info/licenses/LICENSE
bigfoot_video_generator-1767666.962.997.dist-info/METADATA
bigfoot_video_generator-1767666.962.997.dist-info/WHEEL
bigfoot_video_generator-1767666.962.997.dist-info/top_level.txt
bigfoot_video_generator-1767666.962.997.dist-info/RECORD
